tes_client/__init__.py
tes_client-0.2.1.dist-info/LICENSE
tes_client-0.2.1.dist-info/METADATA
tes_client-0.2.1.dist-info/WHEEL
tes_client-0.2.1.dist-info/top_level.txt
tes_client-0.2.1.dist-info/RECORD
