Metadata-Version: 2.1
Name: tes-client
Version: 0.2.1
Summary: bravado generated mock GA4GH TES client
Home-page: https://github.com/elixir-europe/TES-cli
Author: ELIXIR Europe
Author-email: vani11537@one.ducic.ac.in
License: Apache License 2.0
Keywords: ga4gh tes elixir client restful api app openapi swagger python bravado
Platform: UNKNOWN
Classifier: License :: OSI Approved :: Apache Software License
Classifier: Development Status :: 3 - Alpha
Classifier: Intended Audience :: Science/Research
Classifier: Topic :: Scientific/Engineering :: Bio-Informatics
Classifier: Natural Language :: English
Classifier: Programming Language :: Python :: 3.5
Classifier: Programming Language :: Python :: 3.6
Classifier: Programming Language :: Python :: 3.7
Requires-Python: >=3
Requires-Dist: bravado[fido]
